bakery/__init__.py
bakery/apps.py
bakery/feeds.py
bakery/models.py
bakery/static_urls.py
bakery/static_views.py
bakery/tasks.py
bakery/management/__init__.py
bakery/management/commands/__init__.py
bakery/management/commands/build.py
bakery/management/commands/buildserver.py
bakery/management/commands/publish.py
bakery/management/commands/unbuild.py
bakery/management/commands/unpublish.py
bakery/tests/__init__.py
bakery/views/__init__.py
bakery/views/base.py
bakery/views/dates.py
bakery/views/detail.py
bakery/views/list.py
django_bakery-0.13.5.dist-info/LICENSE
django_bakery-0.13.5.dist-info/METADATA
django_bakery-0.13.5.dist-info/WHEEL
django_bakery-0.13.5.dist-info/top_level.txt
django_bakery-0.13.5.dist-info/RECORD
