Metadata-Version: 2.2
Name: django-bakery
Version: 0.13.5
Summary: A set of helpers for baking your Django site out as flat files
Home-page: http://www.github.com/palewire/django-bakery/
Author: Ben Welsh
Author-email: b@palewi.re
License: MIT
Classifier: Development Status :: 5 - Production/Stable
Classifier: Programming Language :: Python
Classifier: Programming Language :: Python :: 3
Classifier: Programming Language :: Python :: 3.9
Classifier: Programming Language :: Python :: 3.10
Classifier: Programming Language :: Python :: 3.11
Classifier: Programming Language :: Python :: 3.12
Classifier: Programming Language :: Python :: 3.13
Classifier: Framework :: Django
Classifier: License :: OSI Approved :: MIT License
License-File: LICENSE
Requires-Dist: six>1.5.2
Requires-Dist: boto3>=1.4.4
Requires-Dist: fs>=2.0.17
Dynamic: author
Dynamic: author-email
Dynamic: classifier
Dynamic: description
Dynamic: description-content-type
Dynamic: home-page
Dynamic: license
Dynamic: requires-dist
Dynamic: summary
